setup.py
justcolumns/__init__.py
justcolumns/test.py
justcolumns/wrapper.py
justcolumns.egg-info/PKG-INFO
justcolumns.egg-info/SOURCES.txt
justcolumns.egg-info/dependency_links.txt
justcolumns.egg-info/requires.txt
justcolumns.egg-info/top_level.txt