Metadata-Version: 1.1
Name: justcolumns
Version: 0.0.2
Summary: UNKNOWN
Home-page: http://github.com/eeue56/just-columns
Author: enalicho
Author-email: enalicho@gmail.com
License: Copyright (c) 2014, eeue56
